exasol/bucketfs/__init__.py
exasol/bucketfs/_buckets.py
exasol/bucketfs/_convert.py
exasol/bucketfs/_error.py
exasol/bucketfs/_logging.py
exasol/bucketfs/_path.py
exasol/bucketfs/_service.py
exasol/bucketfs/_shared.py
exasol/bucketfs/py.typed
exasol/bucketfs/version.py
exasol_bucketfs-2.0.0.dist-info/LICENSE
exasol_bucketfs-2.0.0.dist-info/METADATA
exasol_bucketfs-2.0.0.dist-info/WHEEL
exasol_bucketfs-2.0.0.dist-info/RECORD
