Metadata-Version: 2.3
Name: exasol-bucketfs
Version: 2.0.0
Summary: BucketFS utilities for the Python programming language
License: MIT
Keywords: exasol,bucketfs
Author: Torsten Kilias
Author-email: torsten.kilias@exasol.com
Requires-Python: >=3.10,<4.0
Classifier: License :: OSI Approved :: MIT License
Classifier: Programming Language :: Python :: 3
Classifier: Programming Language :: Python :: 3.10
Classifier: Programming Language :: Python :: 3.11
Classifier: Programming Language :: Python :: 3.12
Classifier: Programming Language :: Python :: 3.13
Requires-Dist: attrs (>=23.2.0)
Requires-Dist: exasol-saas-api (>2.0.0,<3.0)
Requires-Dist: httpx (>=0.27.0)
Requires-Dist: requests (>=2.32.4)
Project-URL: Homepage, https://github.com/exasol/bucketfs-python
Project-URL: Repository, https://github.com/exasol/bucketfs-python
